MANIFEST.in
setup.py
docs/HISTORY.txt
src/dolmen/__init__.py
src/dolmen.app.search.egg-info/PKG-INFO
src/dolmen.app.search.egg-info/SOURCES.txt
src/dolmen.app.search.egg-info/dependency_links.txt
src/dolmen.app.search.egg-info/namespace_packages.txt
src/dolmen.app.search.egg-info/not-zip-safe
src/dolmen.app.search.egg-info/requires.txt
src/dolmen.app.search.egg-info/top_level.txt
src/dolmen/app/__init__.py
src/dolmen/app/search/README.txt
src/dolmen/app/search/__init__.py
src/dolmen/app/search/browser.py
src/dolmen/app/search/configure.zcml
src/dolmen/app/search/ftesting.zcml
src/dolmen/app/search/interfaces.py
src/dolmen/app/search/searchers.py
src/dolmen/app/search/sets.py
src/dolmen/app/search/tests.py
src/dolmen/app/search/browser_templates/results.pt
src/dolmen/app/search/browser_templates/search.pt
src/dolmen/app/search/locales/en/LC_MESSAGES/dolmen.app.search.mo
src/dolmen/app/search/locales/en/LC_MESSAGES/dolmen.app.search.po
src/dolmen/app/search/locales/fr/LC_MESSAGES/dolmen.app.search.mo
src/dolmen/app/search/locales/fr/LC_MESSAGES/dolmen.app.search.po